setup.py
elma/__init__.py
elma/elma_api_web_client.py
elma/exceptions.py
elma/models/__init__.py
elma/models/authorization.py
elma/models/data.py
elma/models/util.py
elma/models/workflow.py
elma_api_lib.egg-info/PKG-INFO
elma_api_lib.egg-info/SOURCES.txt
elma_api_lib.egg-info/dependency_links.txt
elma_api_lib.egg-info/top_level.txt