Metadata-Version: 2.1
Name: elma-api-lib
Version: 1.0.6
Summary: elma api lib
Home-page: https://github.com/evgenykuzin/elma-api-lib
Author: Evgeny Kuzin
Author-email: evgenykuzin21@gmail.com
License: MIT License
Platform: UNKNOWN
